aliyunsdkdt_oc_info/__init__.py
aliyunsdkdt_oc_info/request/__init__.py
aliyunsdkdt_oc_info/request/v20220829/GetOcCompetitorsRequest.py
aliyunsdkdt_oc_info/request/v20220829/GetOcCoreTeamsRequest.py
aliyunsdkdt_oc_info/request/v20220829/GetOcFinancingRequest.py
aliyunsdkdt_oc_info/request/v20220829/GetOcFuzzSearchRequest.py
aliyunsdkdt_oc_info/request/v20220829/GetOcIcAbnormalOperationRequest.py
aliyunsdkdt_oc_info/request/v20220829/GetOcIcAdminLicenseRequest.py
aliyunsdkdt_oc_info/request/v20220829/GetOcIcBasicRequest.py
aliyunsdkdt_oc_info/request/v20220829/GetOcIcBranchRequest.py
aliyunsdkdt_oc_info/request/v20220829/GetOcIcChangeRecordRequest.py
aliyunsdkdt_oc_info/request/v20220829/GetOcIcCheckupRequest.py
aliyunsdkdt_oc_info/request/v20220829/GetOcIcClearAccountRequest.py
aliyunsdkdt_oc_info/request/v20220829/GetOcIcDoubleCheckupRequest.py
aliyunsdkdt_oc_info/request/v20220829/GetOcIcEmployeeRequest.py
aliyunsdkdt_oc_info/request/v20220829/GetOcIcEquityFrozenRequest.py
aliyunsdkdt_oc_info/request/v20220829/GetOcIcEquityPledgeRequest.py
aliyunsdkdt_oc_info/request/v20220829/GetOcIcInvestmentRequest.py
aliyunsdkdt_oc_info/request/v20220829/GetOcIcKnowledgePropertyPledgeRequest.py
aliyunsdkdt_oc_info/request/v20220829/GetOcIcMortgageRequest.py
aliyunsdkdt_oc_info/request/v20220829/GetOcIcSeriousOffenseRequest.py
aliyunsdkdt_oc_info/request/v20220829/GetOcIcShareholderRequest.py
aliyunsdkdt_oc_info/request/v20220829/GetOcIcSimpleCancelRequest.py
aliyunsdkdt_oc_info/request/v20220829/GetOcIpCertificateRequest.py
aliyunsdkdt_oc_info/request/v20220829/GetOcIpDomainRequest.py
aliyunsdkdt_oc_info/request/v20220829/GetOcIpPatentRequest.py
aliyunsdkdt_oc_info/request/v20220829/GetOcIpSoftwareCopyrightRequest.py
aliyunsdkdt_oc_info/request/v20220829/GetOcIpTrademarkRequest.py
aliyunsdkdt_oc_info/request/v20220829/GetOcIpWorksCopyrightRequest.py
aliyunsdkdt_oc_info/request/v20220829/GetOcJusticeAuctionRequest.py
aliyun_python_sdk_dt_oc_info-1.0.0.dist-info/LICENSE
aliyun_python_sdk_dt_oc_info-1.0.0.dist-info/METADATA
aliyun_python_sdk_dt_oc_info-1.0.0.dist-info/WHEEL
aliyun_python_sdk_dt_oc_info-1.0.0.dist-info/top_level.txt
aliyun_python_sdk_dt_oc_info-1.0.0.dist-info/RECORD
